Metadata-Version: 1.0
Name: pybility
Version: 1.0.2
Summary: Python probability distribution sampling and plotting
Home-page: https://pypi.org/project/pybility/
Author: Marios Tsatsos
Author-email: mariostsatsos@gmail.com
License: MIT
Platform: UNKNOWN
